{"sections":{"main":{"type":"main-page","disabled":true,"settings":{"padding_top":28,"padding_bottom":28}},"filter_collection_list_mwedTi":{"type":"filter-collection-list","blocks":{"collection_97rwx7":{"type":"collection","settings":{"collection":"fits-everybody","custom_title":"","custom_image":"shopify:\/\/shop_images\/24cf9cd90c9d452ac91632e26224a20eb845c295-670x812.avif","category":"women"}},"collection_fBPE4h":{"type":"collection","settings":{"collection":"cotton","custom_title":"","custom_image":"shopify:\/\/shop_images\/e8fb40ade7db9bc5fb5cb6fe24b003beef7dba89-670x812.avif","category":"women"}},"collection_Kj6kEa":{"type":"collection","settings":{"collection":"seamless-sculpt","custom_title":"","custom_image":"shopify:\/\/shop_images\/3bb20c957c38823359dfe61d08654faf08fe767f-670x812.avif","category":"women"}},"collection_cHzj84":{"type":"collection","settings":{"collection":"skims-stretch","custom_title":"","custom_image":"shopify:\/\/shop_images\/8e6e5b18376e1637c63bb7830f980db149cbbb78-670x812_1.avif","category":"women"}},"collection_dbEwUg":{"type":"collection","settings":{"collection":"soft-lounge","custom_title":"","custom_image":"shopify:\/\/shop_images\/a7c091ba36caabd76c06fb6389bf8b2a4cbc2e46-670x812.avif","category":"women"}},"collection_fDBcUw":{"type":"collection","settings":{"collection":"skims-cotton","custom_title":"","custom_image":"shopify:\/\/shop_images\/c52334e1f4a96b6015a3c74e0ea771389e01b28a-670x812.avif","category":"men"}},"collection_UTHKJm":{"type":"collection","settings":{"collection":"skims-stretch","custom_title":"","custom_image":"shopify:\/\/shop_images\/dbc3c1ebd521288edc14e5b497c283f035c08a09-670x812.avif","category":"men"}},"collection_KQdKBy":{"type":"collection","settings":{"collection":"skims-stretch","custom_title":"CREAMY FLEX","custom_image":"shopify:\/\/shop_images\/a4858bd410bff22223510cf1be2be9295a5b5f6a-670x812.avif","category":"men"}},"collection_DgEBDJ":{"type":"collection","settings":{"collection":"skims-stretch","custom_title":"JERSEY LAUNGE","custom_image":"shopify:\/\/shop_images\/c43f8b655055b386c5a3f139fadf57833d7722a3-670x812.avif","category":"men"}},"collection_rNbxCU":{"type":"collection","settings":{"collection":"skims-stretch","custom_title":"FLEECE LOUNGE","custom_image":"shopify:\/\/shop_images\/6fa0675b36364674793b8ce4c2c29d1ce31fe3fa-670x812.avif","category":"men"}}},"block_order":["collection_97rwx7","collection_fBPE4h","collection_Kj6kEa","collection_cHzj84","collection_dbEwUg","collection_fDBcUw","collection_UTHKJm","collection_KQdKBy","collection_DgEBDJ","collection_rNbxCU"],"name":"Collection List with Filter","settings":{"heading":"CREAMY Collections","subheading":"A Collection for Every Body"}},"image_with_text_iUJxmr":{"type":"image-with-text","blocks":{"heading_cM9kkm":{"type":"heading","settings":{"heading":"Looking for Something New?","heading_size":"h2"}},"text_BEjxqH":{"type":"text","settings":{"text":"<p>Don’t miss the drops everyone’s talking about. Shop our latest collections now! They’re going to look so good on you.<br\/><br\/><\/p>","text_style":"body"}},"button_nEUqEn":{"type":"button","settings":{"button_label":"SHOP NEW ARRIVALS","button_link":"shopify:\/\/collections\/new-arrival","button_style_secondary":false}}},"block_order":["heading_cM9kkm","text_BEjxqH","button_nEUqEn"],"custom_css":["p {letter-spacing: 0; color: #2d2a26;}","h2.image-with-text__heading.inline-richtext.h2 {letter-spacing: 0;}"],"name":"t:sections.image-with-text.presets.name","settings":{"image":"shopify:\/\/shop_images\/ddbfa17d85c182a3f84b6944da9a3f064ed18f5e-800x1000.avif","height":"adapt","desktop_image_width":"medium","layout":"image_first","image_behavior":"none","content_layout":"no-overlap","desktop_content_position":"middle","desktop_content_alignment":"center","mobile_content_alignment":"center","section_color_scheme":"","color_scheme":"","padding_top":36,"padding_bottom":36}}},"order":["main","filter_collection_list_mwedTi","image_with_text_iUJxmr"]}